mem.v
// mem.v - simple synchronous memory model (word addressed)
// size: 256 words (16-bit each)
module mem(
    input clk,
    input [15:0] addr,
    input [15:0] wdata,
    input we,
    output reg [15:0] rdata
);
    reg [15:0] mem_array [0:255];

    initial begin
        // optionally load a hex file here:
        $readmemh("mem_init.hex", mem_array);
    end

    always @(posedge clk) begin
        if (we) begin
            mem_array[addr] <= wdata;
        end
        rdata <= mem_array[addr];
    end

    // for debug
    task dump_mem;
        input integer start, finish;
        integer i;
        begin
            for (i = start; i <= finish; i = i + 1)
                $display("MEM[%0d] = %0h", i, mem_array[i]);
        end
    endtask
endmodule

cpu.v
// cpu.v - simple single-cycle 16-bit RISC CPU
module cpu(
    input clk,
    input rst,
    output reg halted,
    // memory interface (word addressed, synchronous read via mem module)
    output reg [15:0] mem_addr,
    input  [15:0] mem_rdata,
    output reg [15:0] mem_wdata,
    output reg mem_we
);
    reg [15:0] pc;
    reg [15:0] inst;

    // register file: 16 x 16-bit
    reg [15:0] regfile [0:15];

    // instruction fields
    wire [3:0] opcode = inst[15:12];
    wire [3:0] rd     = inst[11:8];
    wire [3:0] rs     = inst[7:4];
    wire [3:0] rt     = inst[3:0];
    wire [7:0] imm8   = inst[7:0];
    wire [3:0] off4   = inst[3:0];
    wire [3:0] base4  = inst[7:4];
    wire [3:0] rs_br  = inst[11:8];
    wire [3:0] rt_br  = inst[7:4];

    // sign-extend helpers
    function [15:0] sign_ext4;
        input [3:0] x; begin
            sign_ext4 = {{12{x[3]}}, x};
        end
    endfunction

    function [15:0] sign_ext8;
        input [7:0] x; begin
            sign_ext8 = {{8{x[7]}}, x};
        end
    endfunction

    // ALU result
    reg [15:0] alu_out;

    // synchronous fetch on rising edge (simple single-cycle)
    always @(posedge clk) begin
        if (rst) begin
            pc <= 16'd0;
            halted <= 0;
            mem_we <= 0;
            mem_addr <= 16'd0;
            mem_wdata <= 16'd0;
            // zero registers
            regfile[0] <= 16'd0;
            regfile[1] <= 16'd0;
            regfile[2] <= 16'd0;
            regfile[3] <= 16'd0;
            regfile[4] <= 16'd0;
            regfile[5] <= 16'd0;
            regfile[6] <= 16'd0;
            regfile[7] <= 16'd0;
            regfile[8] <= 16'd0;
            regfile[9] <= 16'd0;
            regfile[10] <= 16'd0;
            regfile[11] <= 16'd0;
            regfile[12] <= 16'd0;
            regfile[13] <= 16'd0;
            regfile[14] <= 16'd0;
            regfile[15] <= 16'd0;
        end else if (!halted) begin
            // Fetch instruction (memory word)
            mem_addr <= pc;
            mem_we <= 0;
            inst <= mem_rdata;

            // decode & execute immediately (single cycle)
            case (opcode)
                4'h0: begin // ADD rd = rs + rt
                    alu_out = regfile[rs] + regfile[rt];
                    regfile[rd] <= alu_out;
                    pc <= pc + 1;
                end
                4'h1: begin // SUB
                    alu_out = regfile[rs] - regfile[rt];
                    regfile[rd] <= alu_out;
                    pc <= pc + 1;
                end
                4'h2: begin // AND
                    regfile[rd] <= regfile[rs] & regfile[rt];
                    pc <= pc + 1;
                end
                4'h3: begin // OR
                    regfile[rd] <= regfile[rs] | regfile[rt];
                    pc <= pc + 1;
                end
                4'h4: begin // XOR
                    regfile[rd] <= regfile[rs] ^ regfile[rt];
                    pc <= pc + 1;
                end
                4'h5: begin // SLT (unsigned)
                    regfile[rd] <= (regfile[rs] < regfile[rt]) ? 16'd1 : 16'd0;
                    pc <= pc + 1;
                end
                4'h6: begin // ADDI rd = rd + sign_ext(imm8)
                    regfile[rd] <= regfile[rd] + sign_ext8(imm8);
                    pc <= pc + 1;
                end
                4'h7: begin // LOADI rd = imm8 (zero-extend)
                    regfile[rd] <= {8'd0, imm8};
                    pc <= pc + 1;
                end
                4'h8: begin // LD rd, base+off4
                    mem_addr <= regfile[base4] + sign_ext4(off4);
                    mem_we <= 0;
                    // read mem_rdata next cycle - but for simplicity we assume mem_rdata is valid this cycle
                    regfile[rd] <= mem_rdata;
                    pc <= pc + 1;
                end
                4'h9: begin // ST rd -> [base+off4]
                    mem_addr <= regfile[base4] + sign_ext4(off4);
                    mem_wdata <= regfile[rd];
                    mem_we <= 1;
                    pc <= pc + 1;
                end
                4'hA: begin // BEQ
                    if (regfile[rs_br] == regfile[rt_br])
                        pc <= pc + sign_ext4(off4);
                    else
                        pc <= pc + 1;
                    mem_we <= 0;
                end
                4'hB: begin // BNE
                    if (regfile[rs_br] != regfile[rt_br])
                        pc <= pc + sign_ext4(off4);
                    else
                        pc <= pc + 1;
                    mem_we <= 0;
                end
                4'hC: begin // JUMP (absolute imm8)
                    pc <= {8'd0, imm8};
                    mem_we <= 0;
                end
                4'hD: begin // HALT
                    halted <= 1;
                    mem_we <= 0;
                end
                default: begin
                    pc <= pc + 1;
                    mem_we <= 0;
                end
            endcase
        end
    end
endmodule

tb.v
`timescale 1ns/1ps
module tb;
    reg clk;
    reg rst;
    wire halted;
    wire [15:0] mem_addr;
    wire [15:0] mem_wdata;
    wire mem_we;
    wire [15:0] mem_rdata;

    // instantiate CPU
    cpu DUT(
        .clk(clk),
        .rst(rst),
        .halted(halted),
        .mem_addr(mem_addr),
        .mem_rdata(mem_rdata),
        .mem_wdata(mem_wdata),
        .mem_we(mem_we)
    );

    // instantiate mem
    mem MEM(
        .clk(clk),
        .addr(mem_addr),
        .wdata(mem_wdata),
        .we(mem_we),
        .rdata(mem_rdata)
    );

    initial begin
        $dumpfile("cpu.vcd");
        $dumpvars(0, tb);
        clk = 0;
        rst = 1;
        #20;
        rst = 0;

        // run until HALT or timeout
        repeat (1000) begin
            #10;
            if (halted) begin
                $display("CPU halted at time %0t", $time);
                // dump registers for inspection by calling internal regfile (only for simulation)
                $display("Register file dump:");
                $display("R0=%h R1=%h R2=%h R3=%h", DUT.regfile[0], DUT.regfile[1], DUT.regfile[2], DUT.regfile[3]);
                $display("R4=%h R5=%h R6=%h R7=%h", DUT.regfile[4], DUT.regfile[5], DUT.regfile[6], DUT.regfile[7]);
                $display("R8=%h R9=%h R10=%h R11=%h", DUT.regfile[8], DUT.regfile[9], DUT.regfile[10], DUT.regfile[11]);
                $display("R12=%h R13=%h R14=%h R15=%h", DUT.regfile[12], DUT.regfile[13], DUT.regfile[14], DUT.regfile[15]);
                #10;
                $finish;
            end
        end
        $display("Timeout - finishing");
        $finish;
    end

    // clock
    always #5 clk = ~clk;
endmodule

cpu.vcd
$date
	Mon Oct 27 17:39:00 2025
$end
$version
	Icarus Verilog
$end
$timescale
	1ps
$end
$scope module tb $end
$var wire 1 ! mem_we $end
$var wire 16 " mem_wdata [15:0] $end
$var wire 16 # mem_rdata [15:0] $end
$var wire 16 $ mem_addr [15:0] $end
$var wire 1 % halted $end
$var reg 1 & clk $end
$var reg 1 ' rst $end
$scope module DUT $end
$var wire 1 & clk $end
$var wire 1 ' rst $end
$var wire 4 ( rt_br [3:0] $end
$var wire 4 ) rt [3:0] $end
$var wire 4 * rs_br [3:0] $end
$var wire 4 + rs [3:0] $end
$var wire 4 , rd [3:0] $end
$var wire 4 - opcode [3:0] $end
$var wire 4 . off4 [3:0] $end
$var wire 16 / mem_rdata [15:0] $end
$var wire 8 0 imm8 [7:0] $end
$var wire 4 1 base4 [3:0] $end
$var reg 16 2 alu_out [15:0] $end
$var reg 1 % halted $end
$var reg 16 3 inst [15:0] $end
$var reg 16 4 mem_addr [15:0] $end
$var reg 16 5 mem_wdata [15:0] $end
$var reg 1 ! mem_we $end
$var reg 16 6 pc [15:0] $end
$scope function sign_ext4 $end
$var reg 4 7 x [3:0] $end
$upscope $end
$scope function sign_ext8 $end
$var reg 8 8 x [7:0] $end
$upscope $end
$upscope $end
$scope module MEM $end
$var wire 16 9 addr [15:0] $end
$var wire 1 & clk $end
$var wire 16 : wdata [15:0] $end
$var wire 1 ! we $end
$var reg 16 ; rdata [15:0] $end
$scope task dump_mem $end
$var integer 32 < finish [31:0] $end
$var integer 32 = i [31:0] $end
$var integer 32 > start [31:0] $end
$upscope $end
$upscope $end
$upscope $end
$enddefinitions $end
$comment Show the parameter values. $end
$dumpall
$end
#0
$dumpvars
bx >
bx =
bx <
bx ;
bx :
bx 9
bx 8
bx 7
bx 6
bx 5
bx 4
bx 3
bx 2
bx 1
bx 0
bx /
bx .
bx -
bx ,
bx +
bx *
bx )
bx (
1'
0&
x%
bx $
bx #
bx "
x!
$end
#5000
b0 "
b0 5
b0 :
b0 $
b0 4
b0 9
0!
0%
b0 6
1&
#10000
0&
#15000
b1 #
b1 /
b1 ;
1&
#20000
0&
0'
#25000
b0 -
b0 ,
b0 +
b1 )
b1 0
b1 .
b0 1
b0 *
b0 (
b1 6
b1 3
1&
#30000
0&
#35000
b10 6
b1 $
b1 4
b1 9
b0 2
1&
#40000
0&
#45000
b11 6
b10 $
b10 4
b10 9
b1000000000010 #
b1000000000010 /
b1000000000010 ;
1&
#50000
0&
#55000
b1 -
b10 )
b10 0
b10 .
b10000000000011 #
b10000000000011 /
b10000000000011 ;
b100 6
b1000000000010 3
b11 $
b11 4
b11 9
1&
#60000
0&
#65000
b10 -
b11 )
b11 0
b11 .
b101 6
b10000000000011 3
b100 $
b100 4
b100 9
b1111000000000000 #
b1111000000000000 /
b1111000000000000 ;
1&
#70000
0&
#75000
b1111 -
b0 )
b0 0
b0 .
bx #
bx /
bx ;
b110 6
b1111000000000000 3
b101 $
b101 4
b101 9
1&
#80000
0&
#85000
bx -
bx ,
bx +
bx )
bx 0
bx .
bx 1
bx *
bx (
b111 6
bx 3
b110 $
b110 4
b110 9
1&
#90000
0&
#95000
b1000 6
b111 $
b111 4
b111 9
1&
#100000
0&
#105000
b1001 6
b1000 $
b1000 4
b1000 9
1&
#110000
0&
#115000
b1010 6
b1001 $
b1001 4
b1001 9
1&
#120000
0&
#125000
b1011 6
b1010 $
b1010 4
b1010 9
1&
#130000
0&
#135000
b1100 6
b1011 $
b1011 4
b1011 9
1&
#140000
0&
#145000
b1101 6
b1100 $
b1100 4
b1100 9
1&
#150000
0&
#155000
b1110 6
b1101 $
b1101 4
b1101 9
1&
#160000
0&
#165000
b1111 6
b1110 $
b1110 4
b1110 9
1&
#170000
0&
#175000
b10000 6
b1111 $
b1111 4
b1111 9
1&
#180000
0&
#185000
b10001 6
b10000 $
b10000 4
b10000 9
1&
#190000
0&
#195000
b10010 6
b10001 $
b10001 4
b10001 9
1&
#200000
0&
#205000
b10011 6
b10010 $
b10010 4
b10010 9
1&
#210000
0&
#215000
b10100 6
b10011 $
b10011 4
b10011 9
1&
#220000
0&
#225000
b10101 6
b10100 $
b10100 4
b10100 9
1&
#230000
0&
#235000
b10110 6
b10101 $
b10101 4
b10101 9
1&
#240000
0&
#245000
b10111 6
b10110 $
b10110 4
b10110 9
1&
#250000
0&
#255000
b11000 6
b10111 $
b10111 4
b10111 9
1&
#260000
0&
#265000
b11001 6
b11000 $
b11000 4
b11000 9
1&
#270000
0&
#275000
b11010 6
b11001 $
b11001 4
b11001 9
1&
#280000
0&
#285000
b11011 6
b11010 $
b11010 4
b11010 9
1&
#290000
0&
#295000
b11100 6
b11011 $
b11011 4
b11011 9
1&
#300000
0&
#305000
b11101 6
b11100 $
b11100 4
b11100 9
1&
#310000
0&
#315000
b11110 6
b11101 $
b11101 4
b11101 9
1&
#320000
0&
#325000
b11111 6
b11110 $
b11110 4
b11110 9
1&
#330000
0&
#335000
b100000 6
b11111 $
b11111 4
b11111 9
1&
#340000
0&
#345000
b100001 6
b100000 $
b100000 4
b100000 9
1&
#350000
0&
#355000
b100010 6
b100001 $
b100001 4
b100001 9
1&
#360000
0&
#365000
b100011 6
b100010 $
b100010 4
b100010 9
1&
#370000
0&
#375000
b100100 6
b100011 $
b100011 4
b100011 9
1&
#380000
0&
#385000
b100101 6
b100100 $
b100100 4
b100100 9
1&
#390000
0&
#395000
b100110 6
b100101 $
b100101 4
b100101 9
1&
#400000
0&
#405000
b100111 6
b100110 $
b100110 4
b100110 9
1&
#410000
0&
#415000
b101000 6
b100111 $
b100111 4
b100111 9
1&
#420000
0&
#425000
b101001 6
b101000 $
b101000 4
b101000 9
1&
#430000
0&
#435000
b101010 6
b101001 $
b101001 4
b101001 9
1&
#440000
0&
#445000
b101011 6
b101010 $
b101010 4
b101010 9
1&
#450000
0&
#455000
b101100 6
b101011 $
b101011 4
b101011 9
1&
#460000
0&
#465000
b101101 6
b101100 $
b101100 4
b101100 9
1&
#470000
0&
#475000
b101110 6
b101101 $
b101101 4
b101101 9
1&
#480000
0&
#485000
b101111 6
b101110 $
b101110 4
b101110 9
1&
#490000
0&
#495000
b110000 6
b101111 $
b101111 4
b101111 9
1&
#500000
0&
#505000
b110001 6
b110000 $
b110000 4
b110000 9
1&
#510000
0&
#515000
b110010 6
b110001 $
b110001 4
b110001 9
1&
#520000
0&
#525000
b110011 6
b110010 $
b110010 4
b110010 9
1&
#530000
0&
#535000
b110100 6
b110011 $
b110011 4
b110011 9
1&
#540000
0&
#545000
b110101 6
b110100 $
b110100 4
b110100 9
1&
#550000
0&
#555000
b110110 6
b110101 $
b110101 4
b110101 9
1&
#560000
0&
#565000
b110111 6
b110110 $
b110110 4
b110110 9
1&
#570000
0&
#575000
b111000 6
b110111 $
b110111 4
b110111 9
1&
#580000
0&
#585000
b111001 6
b111000 $
b111000 4
b111000 9
1&
#590000
0&
#595000
b111010 6
b111001 $
b111001 4
b111001 9
1&
#600000
0&
#605000
b111011 6
b111010 $
b111010 4
b111010 9
1&
#610000
0&
#615000
b111100 6
b111011 $
b111011 4
b111011 9
1&
#620000
0&
#625000
b111101 6
b111100 $
b111100 4
b111100 9
1&
#630000
0&
#635000
b111110 6
b111101 $
b111101 4
b111101 9
1&
#640000
0&
#645000
b111111 6
b111110 $
b111110 4
b111110 9
1&
#650000
0&
#655000
b1000000 6
b111111 $
b111111 4
b111111 9
1&
#660000
0&
#665000
b1000001 6
b1000000 $
b1000000 4
b1000000 9
1&
#670000
0&
#675000
b1000010 6
b1000001 $
b1000001 4
b1000001 9
1&
#680000
0&
#685000
b1000011 6
b1000010 $
b1000010 4
b1000010 9
1&
#690000
0&
#695000
b1000100 6
b1000011 $
b1000011 4
b1000011 9
1&
#700000
0&
#705000
b1000101 6
b1000100 $
b1000100 4
b1000100 9
1&
#710000
0&
#715000
b1000110 6
b1000101 $
b1000101 4
b1000101 9
1&
#720000
0&
#725000
b1000111 6
b1000110 $
b1000110 4
b1000110 9
1&
#730000
0&
#735000
b1001000 6
b1000111 $
b1000111 4
b1000111 9
1&
#740000
0&
#745000
b1001001 6
b1001000 $
b1001000 4
b1001000 9
1&
#750000
0&
#755000
b1001010 6
b1001001 $
b1001001 4
b1001001 9
1&
#760000
0&
#765000
b1001011 6
b1001010 $
b1001010 4
b1001010 9
1&
#770000
0&
#775000
b1001100 6
b1001011 $
b1001011 4
b1001011 9
1&
#780000
0&
#785000
b1001101 6
b1001100 $
b1001100 4
b1001100 9
1&
#790000
0&
#795000
b1001110 6
b1001101 $
b1001101 4
b1001101 9
1&
#800000
0&
#805000
b1001111 6
b1001110 $
b1001110 4
b1001110 9
1&
#810000
0&
#815000
b1010000 6
b1001111 $
b1001111 4
b1001111 9
1&
#820000
0&
#825000
b1010001 6
b1010000 $
b1010000 4
b1010000 9
1&
#830000
0&
#835000
b1010010 6
b1010001 $
b1010001 4
b1010001 9
1&
#840000
0&
#845000
b1010011 6
b1010010 $
b1010010 4
b1010010 9
1&
#850000
0&
#855000
b1010100 6
b1010011 $
b1010011 4
b1010011 9
1&
#860000
0&
#865000
b1010101 6
b1010100 $
b1010100 4
b1010100 9
1&
#870000
0&
#875000
b1010110 6
b1010101 $
b1010101 4
b1010101 9
1&
#880000
0&
#885000
b1010111 6
b1010110 $
b1010110 4
b1010110 9
1&
#890000
0&
#895000
b1011000 6
b1010111 $
b1010111 4
b1010111 9
1&
#900000
0&
#905000
b1011001 6
b1011000 $
b1011000 4
b1011000 9
1&
#910000
0&
#915000
b1011010 6
b1011001 $
b1011001 4
b1011001 9
1&
#920000
0&
#925000
b1011011 6
b1011010 $
b1011010 4
b1011010 9
1&
#930000
0&
#935000
b1011100 6
b1011011 $
b1011011 4
b1011011 9
1&
#940000
0&
#945000
b1011101 6
b1011100 $
b1011100 4
b1011100 9
1&
#950000
0&
#955000
b1011110 6
b1011101 $
b1011101 4
b1011101 9
1&
#960000
0&
#965000
b1011111 6
b1011110 $
b1011110 4
b1011110 9
1&
#970000
0&
#975000
b1100000 6
b1011111 $
b1011111 4
b1011111 9
1&
#980000
0&
#985000
b1100001 6
b1100000 $
b1100000 4
b1100000 9
1&
#990000
0&
#995000
b1100010 6
b1100001 $
b1100001 4
b1100001 9
1&
#1000000
0&
#1005000
b1100011 6
b1100010 $
b1100010 4
b1100010 9
1&
#1010000
0&
#1015000
b1100100 6
b1100011 $
b1100011 4
b1100011 9
1&
#1020000
0&
#1025000
b1100101 6
b1100100 $
b1100100 4
b1100100 9
1&
#1030000
0&
#1035000
b1100110 6
b1100101 $
b1100101 4
b1100101 9
1&
#1040000
0&
#1045000
b1100111 6
b1100110 $
b1100110 4
b1100110 9
1&
#1050000
0&
#1055000
b1101000 6
b1100111 $
b1100111 4
b1100111 9
1&
#1060000
0&
#1065000
b1101001 6
b1101000 $
b1101000 4
b1101000 9
1&
#1070000
0&
#1075000
b1101010 6
b1101001 $
b1101001 4
b1101001 9
1&
#1080000
0&
#1085000
b1101011 6
b1101010 $
b1101010 4
b1101010 9
1&
#1090000
0&
#1095000
b1101100 6
b1101011 $
b1101011 4
b1101011 9
1&
#1100000
0&
#1105000
b1101101 6
b1101100 $
b1101100 4
b1101100 9
1&
#1110000
0&
#1115000
b1101110 6
b1101101 $
b1101101 4
b1101101 9
1&
#1120000
0&
#1125000
b1101111 6
b1101110 $
b1101110 4
b1101110 9
1&
#1130000
0&
#1135000
b1110000 6
b1101111 $
b1101111 4
b1101111 9
1&
#1140000
0&
#1145000
b1110001 6
b1110000 $
b1110000 4
b1110000 9
1&
#1150000
0&
#1155000
b1110010 6
b1110001 $
b1110001 4
b1110001 9
1&
#1160000
0&
#1165000
b1110011 6
b1110010 $
b1110010 4
b1110010 9
1&
#1170000
0&
#1175000
b1110100 6
b1110011 $
b1110011 4
b1110011 9
1&
#1180000
0&
#1185000
b1110101 6
b1110100 $
b1110100 4
b1110100 9
1&
#1190000
0&
#1195000
b1110110 6
b1110101 $
b1110101 4
b1110101 9
1&
#1200000
0&
#1205000
b1110111 6
b1110110 $
b1110110 4
b1110110 9
1&
#1210000
0&
#1215000
b1111000 6
b1110111 $
b1110111 4
b1110111 9
1&
#1220000
0&
#1225000
b1111001 6
b1111000 $
b1111000 4
b1111000 9
1&
#1230000
0&
#1235000
b1111010 6
b1111001 $
b1111001 4
b1111001 9
1&
#1240000
0&
#1245000
b1111011 6
b1111010 $
b1111010 4
b1111010 9
1&
#1250000
0&
#1255000
b1111100 6
b1111011 $
b1111011 4
b1111011 9
1&
#1260000
0&
#1265000
b1111101 6
b1111100 $
b1111100 4
b1111100 9
1&
#1270000
0&
#1275000
b1111110 6
b1111101 $
b1111101 4
b1111101 9
1&
#1280000
0&
#1285000
b1111111 6
b1111110 $
b1111110 4
b1111110 9
1&
#1290000
0&
#1295000
b10000000 6
b1111111 $
b1111111 4
b1111111 9
1&
#1300000
0&
#1305000
b10000001 6
b10000000 $
b10000000 4
b10000000 9
1&
#1310000
0&
#1315000
b10000010 6
b10000001 $
b10000001 4
b10000001 9
1&
#1320000
0&
#1325000
b10000011 6
b10000010 $
b10000010 4
b10000010 9
1&
#1330000
0&
#1335000
b10000100 6
b10000011 $
b10000011 4
b10000011 9
1&
#1340000
0&
#1345000
b10000101 6
b10000100 $
b10000100 4
b10000100 9
1&
#1350000
0&
#1355000
b10000110 6
b10000101 $
b10000101 4
b10000101 9
1&
#1360000
0&
#1365000
b10000111 6
b10000110 $
b10000110 4
b10000110 9
1&
#1370000
0&
#1375000
b10001000 6
b10000111 $
b10000111 4
b10000111 9
1&
#1380000
0&
#1385000
b10001001 6
b10001000 $
b10001000 4
b10001000 9
1&
#1390000
0&
#1395000
b10001010 6
b10001001 $
b10001001 4
b10001001 9
1&
#1400000
0&
#1405000
b10001011 6
b10001010 $
b10001010 4
b10001010 9
1&
#1410000
0&
#1415000
b10001100 6
b10001011 $
b10001011 4
b10001011 9
1&
#1420000
0&
#1425000
b10001101 6
b10001100 $
b10001100 4
b10001100 9
1&
#1430000
0&
#1435000
b10001110 6
b10001101 $
b10001101 4
b10001101 9
1&
#1440000
0&
#1445000
b10001111 6
b10001110 $
b10001110 4
b10001110 9
1&
#1450000
0&
#1455000
b10010000 6
b10001111 $
b10001111 4
b10001111 9
1&
#1460000
0&
#1465000
b10010001 6
b10010000 $
b10010000 4
b10010000 9
1&
#1470000
0&
#1475000
b10010010 6
b10010001 $
b10010001 4
b10010001 9
1&
#1480000
0&
#1485000
b10010011 6
b10010010 $
b10010010 4
b10010010 9
1&
#1490000
0&
#1495000
b10010100 6
b10010011 $
b10010011 4
b10010011 9
1&
#1500000
0&
#1505000
b10010101 6
b10010100 $
b10010100 4
b10010100 9
1&
#1510000
0&
#1515000
b10010110 6
b10010101 $
b10010101 4
b10010101 9
1&
#1520000
0&
#1525000
b10010111 6
b10010110 $
b10010110 4
b10010110 9
1&
#1530000
0&
#1535000
b10011000 6
b10010111 $
b10010111 4
b10010111 9
1&
#1540000
0&
#1545000
b10011001 6
b10011000 $
b10011000 4
b10011000 9
1&
#1550000
0&
#1555000
b10011010 6
b10011001 $
b10011001 4
b10011001 9
1&
#1560000
0&
#1565000
b10011011 6
b10011010 $
b10011010 4
b10011010 9
1&
#1570000
0&
#1575000
b10011100 6
b10011011 $
b10011011 4
b10011011 9
1&
#1580000
0&
#1585000
b10011101 6
b10011100 $
b10011100 4
b10011100 9
1&
#1590000
0&
#1595000
b10011110 6
b10011101 $
b10011101 4
b10011101 9
1&
#1600000
0&
#1605000
b10011111 6
b10011110 $
b10011110 4
b10011110 9
1&
#1610000
0&
#1615000
b10100000 6
b10011111 $
b10011111 4
b10011111 9
1&
#1620000
0&
#1625000
b10100001 6
b10100000 $
b10100000 4
b10100000 9
1&
#1630000
0&
#1635000
b10100010 6
b10100001 $
b10100001 4
b10100001 9
1&
#1640000
0&
#1645000
b10100011 6
b10100010 $
b10100010 4
b10100010 9
1&
#1650000
0&
#1655000
b10100100 6
b10100011 $
b10100011 4
b10100011 9
1&
#1660000
0&
#1665000
b10100101 6
b10100100 $
b10100100 4
b10100100 9
1&
#1670000
0&
#1675000
b10100110 6
b10100101 $
b10100101 4
b10100101 9
1&
#1680000
0&
#1685000
b10100111 6
b10100110 $
b10100110 4
b10100110 9
1&
#1690000
0&
#1695000
b10101000 6
b10100111 $
b10100111 4
b10100111 9
1&
#1700000
0&
#1705000
b10101001 6
b10101000 $
b10101000 4
b10101000 9
1&
#1710000
0&
#1715000
b10101010 6
b10101001 $
b10101001 4
b10101001 9
1&
#1720000
0&
#1725000
b10101011 6
b10101010 $
b10101010 4
b10101010 9
1&
#1730000
0&
#1735000
b10101100 6
b10101011 $
b10101011 4
b10101011 9
1&
#1740000
0&
#1745000
b10101101 6
b10101100 $
b10101100 4
b10101100 9
1&
#1750000
0&
#1755000
b10101110 6
b10101101 $
b10101101 4
b10101101 9
1&
#1760000
0&
#1765000
b10101111 6
b10101110 $
b10101110 4
b10101110 9
1&
#1770000
0&
#1775000
b10110000 6
b10101111 $
b10101111 4
b10101111 9
1&
#1780000
0&
#1785000
b10110001 6
b10110000 $
b10110000 4
b10110000 9
1&
#1790000
0&
#1795000
b10110010 6
b10110001 $
b10110001 4
b10110001 9
1&
#1800000
0&
#1805000
b10110011 6
b10110010 $
b10110010 4
b10110010 9
1&
#1810000
0&
#1815000
b10110100 6
b10110011 $
b10110011 4
b10110011 9
1&
#1820000
0&
#1825000
b10110101 6
b10110100 $
b10110100 4
b10110100 9
1&
#1830000
0&
#1835000
b10110110 6
b10110101 $
b10110101 4
b10110101 9
1&
#1840000
0&
#1845000
b10110111 6
b10110110 $
b10110110 4
b10110110 9
1&
#1850000
0&
#1855000
b10111000 6
b10110111 $
b10110111 4
b10110111 9
1&
#1860000
0&
#1865000
b10111001 6
b10111000 $
b10111000 4
b10111000 9
1&
#1870000
0&
#1875000
b10111010 6
b10111001 $
b10111001 4
b10111001 9
1&
#1880000
0&
#1885000
b10111011 6
b10111010 $
b10111010 4
b10111010 9
1&
#1890000
0&
#1895000
b10111100 6
b10111011 $
b10111011 4
b10111011 9
1&
#1900000
0&
#1905000
b10111101 6
b10111100 $
b10111100 4
b10111100 9
1&
#1910000
0&
#1915000
b10111110 6
b10111101 $
b10111101 4
b10111101 9
1&
#1920000
0&
#1925000
b10111111 6
b10111110 $
b10111110 4
b10111110 9
1&
#1930000
0&
#1935000
b11000000 6
b10111111 $
b10111111 4
b10111111 9
1&
#1940000
0&
#1945000
b11000001 6
b11000000 $
b11000000 4
b11000000 9
1&
#1950000
0&
#1955000
b11000010 6
b11000001 $
b11000001 4
b11000001 9
1&
#1960000
0&
#1965000
b11000011 6
b11000010 $
b11000010 4
b11000010 9
1&
#1970000
0&
#1975000
b11000100 6
b11000011 $
b11000011 4
b11000011 9
1&
#1980000
0&
#1985000
b11000101 6
b11000100 $
b11000100 4
b11000100 9
1&
#1990000
0&
#1995000
b11000110 6
b11000101 $
b11000101 4
b11000101 9
1&
#2000000
0&
#2005000
b11000111 6
b11000110 $
b11000110 4
b11000110 9
1&
#2010000
0&
#2015000
b11001000 6
b11000111 $
b11000111 4
b11000111 9
1&
#2020000
0&
#2025000
b11001001 6
b11001000 $
b11001000 4
b11001000 9
1&
#2030000
0&
#2035000
b11001010 6
b11001001 $
b11001001 4
b11001001 9
1&
#2040000
0&
#2045000
b11001011 6
b11001010 $
b11001010 4
b11001010 9
1&
#2050000
0&
#2055000
b11001100 6
b11001011 $
b11001011 4
b11001011 9
1&
#2060000
0&
#2065000
b11001101 6
b11001100 $
b11001100 4
b11001100 9
1&
#2070000
0&
#2075000
b11001110 6
b11001101 $
b11001101 4
b11001101 9
1&
#2080000
0&
#2085000
b11001111 6
b11001110 $
b11001110 4
b11001110 9
1&
#2090000
0&
#2095000
b11010000 6
b11001111 $
b11001111 4
b11001111 9
1&
#2100000
0&
#2105000
b11010001 6
b11010000 $
b11010000 4
b11010000 9
1&
#2110000
0&
#2115000
b11010010 6
b11010001 $
b11010001 4
b11010001 9
1&
#2120000
0&
#2125000
b11010011 6
b11010010 $
b11010010 4
b11010010 9
1&
#2130000
0&
#2135000
b11010100 6
b11010011 $
b11010011 4
b11010011 9
1&
#2140000
0&
#2145000
b11010101 6
b11010100 $
b11010100 4
b11010100 9
1&
#2150000
0&
#2155000
b11010110 6
b11010101 $
b11010101 4
b11010101 9
1&
#2160000
0&
#2165000
b11010111 6
b11010110 $
b11010110 4
b11010110 9
1&
#2170000
0&
#2175000
b11011000 6
b11010111 $
b11010111 4
b11010111 9
1&
#2180000
0&
#2185000
b11011001 6
b11011000 $
b11011000 4
b11011000 9
1&
#2190000
0&
#2195000
b11011010 6
b11011001 $
b11011001 4
b11011001 9
1&
#2200000
0&
#2205000
b11011011 6
b11011010 $
b11011010 4
b11011010 9
1&
#2210000
0&
#2215000
b11011100 6
b11011011 $
b11011011 4
b11011011 9
1&
#2220000
0&
#2225000
b11011101 6
b11011100 $
b11011100 4
b11011100 9
1&
#2230000
0&
#2235000
b11011110 6
b11011101 $
b11011101 4
b11011101 9
1&
#2240000
0&
#2245000
b11011111 6
b11011110 $
b11011110 4
b11011110 9
1&
#2250000
0&
#2255000
b11100000 6
b11011111 $
b11011111 4
b11011111 9
1&
#2260000
0&
#2265000
b11100001 6
b11100000 $
b11100000 4
b11100000 9
1&
#2270000
0&
#2275000
b11100010 6
b11100001 $
b11100001 4
b11100001 9
1&
#2280000
0&
#2285000
b11100011 6
b11100010 $
b11100010 4
b11100010 9
1&
#2290000
0&
#2295000
b11100100 6
b11100011 $
b11100011 4
b11100011 9
1&
#2300000
0&
#2305000
b11100101 6
b11100100 $
b11100100 4
b11100100 9
1&
#2310000
0&
#2315000
b11100110 6
b11100101 $
b11100101 4
b11100101 9
1&
#2320000
0&
#2325000
b11100111 6
b11100110 $
b11100110 4
b11100110 9
1&
#2330000
0&
#2335000
b11101000 6
b11100111 $
b11100111 4
b11100111 9
1&
#2340000
0&
#2345000
b11101001 6
b11101000 $
b11101000 4
b11101000 9
1&
#2350000
0&
#2355000
b11101010 6
b11101001 $
b11101001 4
b11101001 9
1&
#2360000
0&
#2365000
b11101011 6
b11101010 $
b11101010 4
b11101010 9
1&
#2370000
0&
#2375000
b11101100 6
b11101011 $
b11101011 4
b11101011 9
1&
#2380000
0&
#2385000
b11101101 6
b11101100 $
b11101100 4
b11101100 9
1&
#2390000
0&
#2395000
b11101110 6
b11101101 $
b11101101 4
b11101101 9
1&
#2400000
0&
#2405000
b11101111 6
b11101110 $
b11101110 4
b11101110 9
1&
#2410000
0&
#2415000
b11110000 6
b11101111 $
b11101111 4
b11101111 9
1&
#2420000
0&
#2425000
b11110001 6
b11110000 $
b11110000 4
b11110000 9
1&
#2430000
0&
#2435000
b11110010 6
b11110001 $
b11110001 4
b11110001 9
1&
#2440000
0&
#2445000
b11110011 6
b11110010 $
b11110010 4
b11110010 9
1&
#2450000
0&
#2455000
b11110100 6
b11110011 $
b11110011 4
b11110011 9
1&
#2460000
0&
#2465000
b11110101 6
b11110100 $
b11110100 4
b11110100 9
1&
#2470000
0&
#2475000
b11110110 6
b11110101 $
b11110101 4
b11110101 9
1&
#2480000
0&
#2485000
b11110111 6
b11110110 $
b11110110 4
b11110110 9
1&
#2490000
0&
#2495000
b11111000 6
b11110111 $
b11110111 4
b11110111 9
1&
#2500000
0&
